CHANGES
LICENSE
MANIFEST.in
README.rst
setup.py
django_sizefield.egg-info/PKG-INFO
django_sizefield.egg-info/SOURCES.txt
django_sizefield.egg-info/dependency_links.txt
django_sizefield.egg-info/not-zip-safe
django_sizefield.egg-info/pbr.json
django_sizefield.egg-info/requires.txt
django_sizefield.egg-info/top_level.txt
sizefield/__init__.py
sizefield/models.py
sizefield/tests.py
sizefield/utils.py
sizefield/widgets.py
sizefield/templatetags/__init__.py
sizefield/templatetags/sizefieldtags.py