Metadata-Version: 1.1
Name: django-sizefield
Version: 0.7
Summary: A model field to store a file size, whose edition and display shows units.
Home-page: https://github.com/leplatrem/django-sizefield
Author: Mathieu Leplatre
Author-email: contact@mathieu-leplatre.info
License: LPGL, see LICENSE file.
Download-URL: http://pypi.python.org/pypi/django-sizefield/
Platform: UNKNOWN
Classifier: Topic :: Utilities
Classifier: Natural Language :: English
Classifier: Operating System :: OS Independent
Classifier: Intended Audience :: Developers
Classifier: Environment :: Web Environment
Classifier: Framework :: Django
Classifier: Development Status :: 5 - Production/Stable
Classifier: Programming Language :: Python :: 2.7
